hextools/__init__.py
hextools/_version.py
hextools/_version.pyi
hextools/handlers.py
hextools/py.typed
hextools/utils.py
hextools/germ/__init__.py
hextools/germ/caproto_ioc.py
hextools/germ/export.py
hextools/germ/ophyd.py
hextools-0.2.3.dist-info/licenses/LICENSE
hextools-0.2.3.dist-info/METADATA
hextools-0.2.3.dist-info/WHEEL
hextools-0.2.3.dist-info/entry_points.txt
hextools-0.2.3.dist-info/top_level.txt
hextools-0.2.3.dist-info/RECORD
