Metadata-Version: 2.4
Name: hextools
Version: 0.2.3
Summary: Tools for NSLS-II HEX beamline
Author-email: Brookhaven National Laboratory <mrakitin@bnl.gov>
License: BSD 3-Clause License
Project-URL: Homepage, https://github.com/NSLS-II-HEX/hextools
Project-URL: Bug Tracker, https://github.com/NSLS-II-HEX/hextools/issues
Project-URL: Discussions, https://github.com/NSLS-II-HEX/hextools/discussions
Project-URL: Changelog, https://github.com/NSLS-II-HEX/hextools/releases
Classifier: Development Status :: 1 - Planning
Classifier: Intended Audience :: Science/Research
Classifier: Intended Audience :: Developers
Classifier: License :: OSI Approved :: BSD License
Classifier: Operating System :: OS Independent
Classifier: Programming Language :: Python
Classifier: Programming Language :: Python :: 3
Classifier: Programming Language :: Python :: 3 :: Only
Classifier: Programming Language :: Python :: 3.8
Classifier: Programming Language :: Python :: 3.9
Classifier: Programming Language :: Python :: 3.10
Classifier: Programming Language :: Python :: 3.11
Classifier: Programming Language :: Python :: 3.12
Classifier: Topic :: Scientific/Engineering
Classifier: Typing :: Typed
Requires-Python: >=3.8
License-File: LICENSE
Requires-Dist: area-detector-handlers
Requires-Dist: caproto
Requires-Dist: event-model>=1.21.0
Requires-Dist: h5py
Requires-Dist: numpy
Requires-Dist: ophyd
Requires-Dist: pillow
Requires-Dist: pyepics
Requires-Dist: tifffile
Provides-Extra: test
Requires-Dist: bluesky; extra == "test"
Requires-Dist: databroker; extra == "test"
Requires-Dist: matplotlib; extra == "test"
Requires-Dist: pyarrow; extra == "test"
Requires-Dist: pyqt5>=5.12; extra == "test"
Requires-Dist: pytest>=6; extra == "test"
Requires-Dist: pytest-cov>=3; extra == "test"
Requires-Dist: tiled[client]; extra == "test"
Provides-Extra: dev
Requires-Dist: ipython; extra == "dev"
Requires-Dist: pre-commit; extra == "dev"
Requires-Dist: pylint; extra == "dev"
Requires-Dist: pytest>=6; extra == "dev"
Requires-Dist: pytest-cov>=3; extra == "dev"
Provides-Extra: docs
Requires-Dist: furo>=2023.08.17; extra == "docs"
Requires-Dist: myst_parser>=0.13; extra == "docs"
Requires-Dist: sphinx>=7.0; extra == "docs"
Requires-Dist: sphinx_autodoc_typehints; extra == "docs"
Requires-Dist: sphinx_copybutton; extra == "docs"
Dynamic: license-file
